cloudcompass/__init__.py
cloudcompass/amazonlightsail.py
cloudcompass/request.py
cloudcompass-0.0.6.dist-info/LICENSE
cloudcompass-0.0.6.dist-info/METADATA
cloudcompass-0.0.6.dist-info/WHEEL
cloudcompass-0.0.6.dist-info/top_level.txt
cloudcompass-0.0.6.dist-info/RECORD
