Metadata-Version: 2.1
Name: cloudcompass
Version: 0.0.6
Summary: A pakage for comparing multi cloud services
Home-page: https://github.com/pypa/sampleproject
Author: Zoya Jamadar
Author-email: zoya.lpf20@gmail.com
Project-URL: Bug Tracker, https://github.com/pypa/sampleproject/issues
Classifier: Programming Language :: Python :: 3
Classifier: License :: OSI Approved :: MIT License
Classifier: Operating System :: OS Independent
Requires-Python: >=3.6
License-File: LICENSE
